LICENSE.txt
MANIFEST.in
README.rst
setup.py
big_O.egg-info/PKG-INFO
big_O.egg-info/SOURCES.txt
big_O.egg-info/dependency_links.txt
big_O.egg-info/requires.txt
big_O.egg-info/top_level.txt
big_o/__init__.py
big_o/big_o.py
big_o/complexities.py
big_o/datagen.py
big_o/reports.py
big_o/test/__init__.py
big_o/test/test_big_o.py
big_o/test/test_complexities.py
big_o/test/test_complexityclass_comparisons.py
big_o/test/test_datagen.py
big_o/test/test_reports.py